{"customer_id": "C1", "basket": [{"product_id": "P49", "price": 695}], "date_of_purchase": "2019-01-13 08:16:00"}
{"customer_id": "C6", "basket": [{"product_id": "P13", "price": 1402}, {"product_id": "P18", "price": 1172}, {"product_id": "P14", "price": 1078}], "date_of_purchase": "2019-01-13 22:18:00"}
{"customer_id": "C38", "basket": [{"product_id": "P28", "price": 207}, {"product_id": "P24", "price": 799}, {"product_id": "P27", "price": 1814}], "date_of_purchase": "2019-01-13 18:37:00"}
{"customer_id": "C43", "basket": [{"product_id": "P32", "price": 826}, {"product_id": "P28", "price": 1486}], "date_of_purchase": "2019-01-13 21:06:00"}
{"customer_id": "C57", "basket": [{"product_id": "P03", "price": 1350}, {"product_id": "P05", "price": 312}], "date_of_purchase": "2019-01-13 15:30:00"}
{"customer_id": "C58", "basket": [{"product_id": "P47", "price": 1963}], "date_of_purchase": "2019-01-13 03:35:00"}
{"customer_id": "C60", "basket": [{"product_id": "P56", "price": 1222}], "date_of_purchase": "2019-01-13 09:46:00"}
{"customer_id": "C76", "basket": [{"product_id": "P52", "price": 244}, {"product_id": "P43", "price": 837}], "date_of_purchase": "2019-01-13 05:15:00"}
{"customer_id": "C80", "basket": [{"product_id": "P10", "price": 1488}], "date_of_purchase": "2019-01-13 22:23:00"}
{"customer_id": "C82", "basket": [{"product_id": "P13", "price": 42}, {"product_id": "P21", "price": 1141}], "date_of_purchase": "2019-01-13 06:49:00"}
{"customer_id": "C83", "basket": [{"product_id": "P63", "price": 1721}], "date_of_purchase": "2019-01-13 12:13:00"}
{"customer_id": "C86", "basket": [{"product_id": "P13", "price": 217}, {"product_id": "P16", "price": 1060}], "date_of_purchase": "2019-01-13 09:19:00"}
{"customer_id": "C94", "basket": [{"product_id": "P02", "price": 400}, {"product_id": "P02", "price": 795}], "date_of_purchase": "2019-01-13 18:17:00"}
{"customer_id": "C99", "basket": [{"product_id": "P38", "price": 534}, {"product_id": "P39", "price": 1143}, {"product_id": "P39", "price": 1950}], "date_of_purchase": "2019-01-13 09:37:00"}
{"customer_id": "C100", "basket": [{"product_id": "P36", "price": 294}], "date_of_purchase": "2019-01-13 08:12:00"}
{"customer_id": "C103", "basket": [{"product_id": "P29", "price": 1121}, {"product_id": "P31", "price": 753}, {"product_id": "P22", "price": 1134}], "date_of_purchase": "2019-01-13 03:23:00"}
{"customer_id": "C104", "basket": [{"product_id": "P63", "price": 761}, {"product_id": "P61", "price": 18}], "date_of_purchase": "2019-01-13 16:53:00"}
{"customer_id": "C114", "basket": [{"product_id": "P62", "price": 1169}, {"product_id": "P64", "price": 640}, {"product_id": "P61", "price": 779}], "date_of_purchase": "2019-01-13 15:30:00"}
{"customer_id": "C116", "basket": [{"product_id": "P39", "price": 1008}], "date_of_purchase": "2019-01-13 11:55:00"}
{"customer_id": "C118", "basket": [{"product_id": "P38", "price": 549}, {"product_id": "P40", "price": 385}], "date_of_purchase": "2019-01-13 23:59:00"}
{"customer_id": "C120", "basket": [{"product_id": "P35", "price": 663}], "date_of_purchase": "2019-01-13 12:44:00"}
{"customer_id": "C121", "basket": [{"product_id": "P43", "price": 1386}, {"product_id": "P42", "price": 790}], "date_of_purchase": "2019-01-13 08:41:00"}
{"customer_id": "C131", "basket": [{"product_id": "P48", "price": 329}, {"product_id": "P50", "price": 1322}, {"product_id": "P53", "price": 410}], "date_of_purchase": "2019-01-13 15:21:00"}
{"customer_id": "C133", "basket": [{"product_id": "P61", "price": 1304}, {"product_id": "P61", "price": 164}], "date_of_purchase": "2019-01-13 18:25:00"}
{"customer_id": "C135", "basket": [{"product_id": "P26", "price": 1234}, {"product_id": "P25", "price": 1837}, {"product_id": "P25", "price": 15}], "date_of_purchase": "2019-01-13 22:23:00"}
{"customer_id": "C136", "basket": [{"product_id": "P28", "price": 46}, {"product_id": "P25", "price": 89}], "date_of_purchase": "2019-01-13 11:12:00"}
